Metadata-Version: 2.1
Name: notas-musicais-kylefelipe
Version: 0.1.0
Summary: Notas musicais é um CLI para ajudar na formação de escalas, acordes e campos hamônicos.
License: Beerware
Author: Kyle Felipe Vieira Roberto
Author-email: kylefelipe@gmail.com
Requires-Python: >=3.10,<4.0
Classifier: Development Status :: 5 - Production/Stable
Classifier: Environment :: Console
Classifier: License :: Other/Proprietary License
Classifier: Natural Language :: Portuguese (Brazilian)
Classifier: Programming Language :: Python :: 3
Classifier: Programming Language :: Python :: 3.10
Classifier: Programming Language :: Python :: 3.11
Classifier: Topic :: Education
Requires-Dist: rich (>=13.3.5,<14.0.0)
Requires-Dist: typer (>=0.9.0,<0.10.0)
Project-URL: Bug Tracker, https://github.com/kylefelipe/notas-musicais/issues
Project-URL: Código Fonte, https://github.com/kylefelipe/notas-musicais
Project-URL: Documentação, https://notas-musicais-kylefelipe.readthedocs.io/en/latest/
